example_pkg/__init__.py
libcek-1.0.5.dist-info/LICENSE
libcek-1.0.5.dist-info/METADATA
libcek-1.0.5.dist-info/WHEEL
libcek-1.0.5.dist-info/top_level.txt
libcek-1.0.5.dist-info/RECORD
