Metadata-Version: 2.1
Name: libcek
Version: 1.0.5
Summary: cek's lib
Home-page: https://github.com/erkuo521/libcek
Author: cek
Author-email: erkuo521@126.com
License: UNKNOWN
Platform: UNKNOWN
Classifier: Programming Language :: Python :: 3
Classifier: License :: OSI Approved :: MIT License
Classifier: Operating System :: OS Independent
Requires-Python: >=3.6
